zbinfigs/__init__.py
zbinfigs/collection.py
zbinfigs/utils.py
zbinfigs-0.1.7.dist-info/METADATA
zbinfigs-0.1.7.dist-info/WHEEL
zbinfigs-0.1.7.dist-info/licenses/LICENSE
zbinfigs-0.1.7.dist-info/RECORD
