Metadata-Version: 2.4
Name: zbinfigs
Version: 0.1.7
Summary: A package for figure classification from a zotero collection of scholarly articles
Project-URL: Source Code, https://github.com/spackman/zbinfigs
Author-email: Isaac Spackman <ispackman@mines.edu>
License-File: LICENSE
Classifier: Intended Audience :: Science/Research
Classifier: License :: OSI Approved :: MIT License
Classifier: Operating System :: OS Independent
Classifier: Programming Language :: Python :: 3
Classifier: Topic :: Scientific/Engineering
Classifier: Topic :: Scientific/Engineering :: Information Analysis
Requires-Python: >=3.10
Requires-Dist: beautifulsoup4>=4.2.4
Requires-Dist: marker-pdf>=1.1.0
Requires-Dist: matplotlib>=3.7.1
Requires-Dist: pandas>=2.2.3
Requires-Dist: tqdm>=4.67
Requires-Dist: xhtml2pdf>=0.2.16
Provides-Extra: docs
Requires-Dist: myst-parser>=0.13; extra == 'docs'
Requires-Dist: sphinx-autodoc-typehints; extra == 'docs'
Requires-Dist: sphinx-copybutton; extra == 'docs'
Requires-Dist: sphinx-rtd-theme; extra == 'docs'
Requires-Dist: sphinx>=4.0; extra == 'docs'
Provides-Extra: test
Requires-Dist: coverage; extra == 'test'
Requires-Dist: pytest; extra == 'test'
